{"torch":{"sum":[{"args":[{"name":"input","kwarg":false,"opt":false,"tfjs":"a"},{"name":"dim","kwarg":false,"opt":false,"tfjs":"axis"},{"name":"keepdim","kwarg":true,"opt":true},{"name":"dtype","kwarg":true,"opt":true}],"attrs":["torch","sum"],"name":"sum","tfjs":"sum","tf":"sum"}],"relu":[{"args":[{"name":"input","kwarg":false,"opt":false,"tfjs":"a"},{"name":"inplace","kwarg":true,"opt":true}],"attrs":["torch","nn","functional","relu"],"name":"relu","tfjs":"relu","tf":"relu"}],"conv2d":[{"args":[{"name":"input","kwarg":false,"opt":false,"tfjs":"a"},{"name":"weight","kwarg":false,"opt":false},{"name":"bias","kwarg":true,"opt":true},{"name":"stride","kwarg":true,"opt":true},{"name":"padding","kwarg":true,"opt":true,"tf":"padding"},{"name":"dilation","kwarg":true,"opt":true},{"name":"groups","kwarg":true,"opt":true}],"attrs":["torch","nn","functional","conv2d"],"name":"conv2d","tfjs":"conv2d","tf":"conv2d"}],"conv3d":[{"args":[{"name":"input","kwarg":false,"opt":false,"tfjs":"a"},{"name":"weight","kwarg":false,"opt":false},{"name":"bias","kwarg":true,"opt":true},{"name":"stride","kwarg":true,"opt":true},{"name":"padding","kwarg":true,"opt":true,"tf":"padding"},{"name":"dilation","kwarg":true,"opt":true},{"name":"groups","kwarg":true,"opt":true}],"attrs":["torch","nn","functional","conv3d"],"name":"conv3d","tfjs":"conv3d","tf":"conv3d"}],"gather":[{"args":[{"name":"input","kwarg":false,"opt":false,"tfjs":"a"},{"name":"dim","kwarg":false,"opt":false,"tfjs":"axis"},{"name":"index","kwarg":false,"opt":false},{"name":"out","kwarg":true,"opt":true},{"name":"sparse_grad","kwarg":true,"opt":true}],"attrs":["torch","gather"],"name":"gather","tfjs":"gather","tf":"gather"}],"grad":[{"args":[{"name":"outputs","kwarg":false,"opt":false},{"name":"inputs","kwarg":false,"opt":false},{"name":"grad_outputs","kwarg":true,"opt":true},{"name":"retain_graph","kwarg":true,"opt":true},{"name":"create_graph","kwarg":true,"opt":true},{"name":"only_inputs","kwarg":true,"opt":true},{"name":"allow_unused","kwarg":true,"opt":true}],"attrs":["torch","autograd","grad"],"name":"grad","tfjs":"grad"}],"conv1d":[{"args":[{"name":"input","kwarg":false,"opt":false,"tfjs":"a"},{"name":"weight","kwarg":false,"opt":false},{"name":"bias","kwarg":true,"opt":true},{"name":"stride","kwarg":true,"opt":true,"tfjs":"stride"},{"name":"padding","kwarg":true,"opt":true,"tf":"padding"},{"name":"dilation","kwarg":true,"opt":true,"tfjs":"dilation"},{"name":"groups","kwarg":true,"opt":true}],"attrs":["torch","nn","functional","conv1d"],"name":"conv1d","tfjs":"conv1d","tf":"conv1d"}],"all":[{"args":[{"name":"dim","kwarg":false,"opt":false,"tfjs":"axis"},{"name":"keepdim","kwarg":true,"opt":true},{"name":"out","kwarg":true,"opt":true}],"attrs":["all"],"name":"all","tfjs":"all","tf":"all"}],"any":[{"args":[{"name":"dim","kwarg":false,"opt":false,"tfjs":"axis"},{"name":"keepdim","kwarg":true,"opt":true},{"name":"out","kwarg":true,"opt":true}],"attrs":["any"],"name":"any","tfjs":"any","tf":"any"}],"relu6":[{"args":[{"name":"input","kwarg":false,"opt":false,"tfjs":"a"},{"name":"inplace","kwarg":true,"opt":true}],"attrs":["torch","nn","functional","relu6"],"name":"relu6","tfjs":"relu6","tf":"relu6"}],"elu":[{"args":[{"name":"input","kwarg":false,"opt":false,"tfjs":"a"},{"name":"alpha","kwarg":true,"opt":true,"tf":"alpha"},{"name":"inplace","kwarg":true,"opt":true}],"attrs":["torch","nn","functional","elu"],"name":"elu","tfjs":"elu","tf":"elu"}],"selu":[{"args":[{"name":"input","kwarg":false,"opt":false,"tfjs":"a"},{"name":"inplace","kwarg":true,"opt":true}],"attrs":["torch","nn","functional","selu"],"name":"selu","tfjs":"selu","tf":"selu"}],"prelu":[{"args":[{"name":"input","kwarg":false,"opt":false,"tfjs":"a"},{"name":"weight","kwarg":false,"opt":false}],"attrs":["torch","nn","functional","prelu"],"name":"prelu","tfjs":"prelu","tf":"prelu"}],"logsigmoid":[{"args":[{"name":"input","kwarg":false,"opt":false,"tfjs":"a"}],"attrs":["torch","nn","functional","logsigmoid"],"name":"logsigmoid","tfjs":"logsigmoid"}],"softplus":[{"args":[{"name":"input","kwarg":false,"opt":false,"tfjs":"a"},{"name":"beta","kwarg":true,"opt":true},{"name":"threshold","kwarg":true,"opt":true}],"attrs":["torch","nn","functional","softplus"],"name":"softplus","tfjs":"softplus","tf":"softplus"}],"softmax":[{"args":[{"name":"input","kwarg":false,"opt":false,"tfjs":"a"},{"name":"dim","kwarg":true,"opt":true,"tfjs":"dim"},{"name":"_stacklevel","kwarg":true,"opt":true},{"name":"dtype","kwarg":true,"opt":true}],"attrs":["torch","nn","functional","softmax"],"name":"softmax","tfjs":"softmax","tf":"softmax"}],"tanh":[{"args":[{"name":"input","kwarg":false,"opt":false,"tfjs":"a"},{"name":"out","kwarg":true,"opt":true}],"attrs":["torch","tanh"],"name":"tanh","tfjs":"tanh","tf":"tanh"}],"sigmoid":[{"args":[{"name":"input","kwarg":false,"opt":false,"tfjs":"a"},{"name":"out","kwarg":true,"opt":true}],"attrs":["torch","sigmoid"],"name":"sigmoid","tfjs":"sigmoid","tf":"sigmoid"}],"dropout":[{"args":[{"name":"input","kwarg":false,"opt":false,"tfjs":"a"},{"name":"p","kwarg":true,"opt":true},{"name":"training","kwarg":true,"opt":true},{"name":"inplace","kwarg":true,"opt":true}],"attrs":["torch","nn","functional","dropout"],"name":"dropout","tfjs":"dropout","tf":"dropout"}],"embedding":[{"args":[{"name":"input","kwarg":false,"opt":false,"tfjs":"a"},{"name":"weight","kwarg":false,"opt":false},{"name":"padding_idx","kwarg":true,"opt":true},{"name":"max_norm","kwarg":true,"opt":true},{"name":"norm_type","kwarg":true,"opt":true},{"name":"scale_grad_by_freq","kwarg":true,"opt":true},{"name":"sparse","kwarg":true,"opt":true}],"attrs":["torch","nn","functional","embedding"],"name":"embedding","tfjs":"embedding","tf":"embedding"}],"identity":[{"args":[{"name":"module","kwarg":false,"opt":false},{"name":"name","kwarg":false,"opt":false}],"attrs":["torch","nn","utils","prune","identity"],"name":"identity","tfjs":"identity","tf":"identity"}],"tensor":[{"args":[{"name":"data","kwarg":false,"opt":false},{"name":"dtype","kwarg":true,"opt":true,"tfjs":"dtype","tf":"dtype"},{"name":"device","kwarg":true,"opt":true},{"name":"requires_grad","kwarg":true,"opt":true},{"name":"pin_memory","kwarg":true,"opt":true}],"attrs":["torch","tensor"],"name":"tensor","tfjs":"tensor","tf":"tensor"}],"zeros":[{"args":[{"name":"","kwarg":false,"opt":false},{"name":"out","kwarg":true,"opt":true},{"name":"dtype","kwarg":true,"opt":true,"tf":"dtype"},{"name":"layout","kwarg":true,"opt":true},{"name":"device","kwarg":true,"opt":true},{"name":"requires_grad","kwarg":true,"opt":true}],"attrs":["torch","zeros"],"name":"zeros","tfjs":"zeros","tf":"zeros"}],"ones":[{"args":[{"name":"","kwarg":false,"opt":false},{"name":"out","kwarg":true,"opt":true},{"name":"dtype","kwarg":true,"opt":true,"tf":"dtype"},{"name":"layout","kwarg":true,"opt":true},{"name":"device","kwarg":true,"opt":true},{"name":"requires_grad","kwarg":true,"opt":true}],"attrs":["torch","ones"],"name":"ones","tfjs":"ones","tf":"ones"}],"range":[{"args":[{"name":"end","kwarg":false,"opt":false},{"name":"start","kwarg":true,"opt":true,"tfjs":"start"},{"name":"step","kwarg":true,"opt":true,"tfjs":"step"},{"name":"out","kwarg":true,"opt":true},{"name":"dtype","kwarg":true,"opt":true,"tfjs":"dtype","tf":"dtype"},{"name":"layout","kwarg":true,"opt":true},{"name":"device","kwarg":true,"opt":true},{"name":"requires_grad","kwarg":true,"opt":true}],"attrs":["torch","range"],"name":"range","tfjs":"range","tf":"range"}],"linspace":[{"args":[{"name":"start","kwarg":false,"opt":false,"tfjs":"start","tf":"start"},{"name":"end","kwarg":false,"opt":false},{"name":"steps","kwarg":true,"opt":true},{"name":"out","kwarg":true,"opt":true},{"name":"dtype","kwarg":true,"opt":true},{"name":"layout","kwarg":true,"opt":true},{"name":"device","kwarg":true,"opt":true},{"name":"requires_grad","kwarg":true,"opt":true}],"attrs":["torch","linspace"],"name":"linspace","tfjs":"linspace","tf":"linspace"}],"eye":[{"args":[{"name":"n","kwarg":false,"opt":false},{"name":"m","kwarg":true,"opt":true},{"name":"out","kwarg":true,"opt":true},{"name":"dtype","kwarg":true,"opt":true,"tfjs":"dtype","tf":"dtype"},{"name":"layout","kwarg":true,"opt":true},{"name":"device","kwarg":true,"opt":true},{"name":"requires_grad","kwarg":true,"opt":true}],"attrs":["torch","eye"],"name":"eye","tfjs":"eye","tf":"eye"}],"pad":[{"args":[{"name":"input","kwarg":false,"opt":false,"tfjs":"a"},{"name":"pad","kwarg":false,"opt":false},{"name":"mode","kwarg":true,"opt":true,"tf":"mode"},{"name":"value","kwarg":true,"opt":true}],"attrs":["torch","nn","functional","pad"],"name":"pad","tfjs":"pad","tf":"pad"}],"reshape":[{"args":[{"name":"input","kwarg":false,"opt":false,"tfjs":"a"},{"name":"shape","kwarg":false,"opt":false,"tf":"shape"}],"attrs":["torch","reshape"],"name":"reshape","tfjs":"reshape","tf":"reshape"}],"split":[{"args":[{"name":"tensor","kwarg":false,"opt":false},{"name":"split_size_or_sections","kwarg":false,"opt":false},{"name":"dim","kwarg":true,"opt":true,"tfjs":"axis"}],"attrs":["torch","split"],"name":"split","tfjs":"split","tf":"split"}],"squeeze":[{"args":[{"name":"input","kwarg":false,"opt":false,"tfjs":"a","tf":"input"},{"name":"dim","kwarg":true,"opt":true,"tfjs":"axis"},{"name":"out","kwarg":true,"opt":true}],"attrs":["torch","squeeze"],"name":"squeeze","tfjs":"squeeze","tf":"squeeze"}],"stack":[{"args":[{"name":"tensors","kwarg":false,"opt":false,"tfjs":"tensors"},{"name":"dim","kwarg":true,"opt":true,"tfjs":"axis"},{"name":"out","kwarg":true,"opt":true}],"attrs":["torch","stack"],"name":"stack","tfjs":"stack","tf":"stack"}],"t":[{"args":[{"name":"input","kwarg":false,"opt":false,"tfjs":"a"}],"attrs":["torch","t"],"name":"t","tfjs":"transpose"}],"take":[{"args":[{"name":"input","kwarg":false,"opt":false,"tfjs":"a"},{"name":"index","kwarg":false,"opt":false}],"attrs":["torch","take"],"name":"take","tfjs":"take"}],"transpose":[{"args":[{"name":"input","kwarg":false,"opt":false,"tfjs":"a"},{"name":"dim0","kwarg":false,"opt":false},{"name":"dim1","kwarg":false,"opt":false}],"attrs":["torch","transpose"],"name":"transpose","tfjs":"transpose","tf":"transpose"}],"where":[{"args":[{"name":"condition","kwarg":false,"opt":false,"tfjs":"condition","tf":"condition"}],"attrs":["torch","where"],"name":"where","tfjs":"where","tf":"where"}],"multinomial":[{"args":[{"name":"input","kwarg":false,"opt":false,"tfjs":"a"},{"name":"num_samples","kwarg":false,"opt":false},{"name":"","kwarg":false,"opt":false},{"name":"replacement","kwarg":true,"opt":true},{"name":"generator","kwarg":true,"opt":true},{"name":"out","kwarg":true,"opt":true}],"attrs":["torch","multinomial"],"name":"multinomial","tfjs":"multinomial"}],"abs":[{"args":[{"name":"input","kwarg":false,"opt":false,"tfjs":"a"},{"name":"out","kwarg":true,"opt":true}],"attrs":["torch","abs"],"name":"abs","tfjs":"abs","tf":"abs"}],"acos":[{"args":[{"name":"input","kwarg":false,"opt":false,"tfjs":"a"},{"name":"out","kwarg":true,"opt":true}],"attrs":["torch","acos"],"name":"acos","tfjs":"acos","tf":"acos"}],"add":[{"args":[{"name":"input","kwarg":false,"opt":false,"tfjs":"a"},{"name":"other","kwarg":false,"opt":false,"tfjs":"b"},{"name":"alpha","kwarg":true,"opt":true},{"name":"out","kwarg":true,"opt":true}],"attrs":["torch","add"],"name":"add","tfjs":"add","tf":"add"}],"asin":[{"args":[{"name":"input","kwarg":false,"opt":false,"tfjs":"a"},{"name":"out","kwarg":true,"opt":true}],"attrs":["torch","asin"],"name":"asin","tfjs":"asin","tf":"asin"}],"atan":[{"args":[{"name":"input","kwarg":false,"opt":false,"tfjs":"a"},{"name":"out","kwarg":true,"opt":true}],"attrs":["torch","atan"],"name":"atan","tfjs":"atan","tf":"atan"}],"atan2":[{"args":[{"name":"input","kwarg":false,"opt":false,"tfjs":"a"},{"name":"other","kwarg":false,"opt":false,"tfjs":"b"},{"name":"out","kwarg":true,"opt":true}],"attrs":["torch","atan2"],"name":"atan2","tfjs":"atan2","tf":"atan2"}],"ceil":[{"args":[{"name":"input","kwarg":false,"opt":false,"tfjs":"a"},{"name":"out","kwarg":true,"opt":true}],"attrs":["torch","ceil"],"name":"ceil","tfjs":"ceil","tf":"ceil"}],"cos":[{"args":[{"name":"input","kwarg":false,"opt":false,"tfjs":"a"},{"name":"out","kwarg":true,"opt":true}],"attrs":["torch","cos"],"name":"cos","tfjs":"cos","tf":"cos"}],"cosh":[{"args":[{"name":"input","kwarg":false,"opt":false,"tfjs":"a"},{"name":"out","kwarg":true,"opt":true}],"attrs":["torch","cosh"],"name":"cosh","tfjs":"cosh","tf":"cosh"}],"div":[{"args":[{"name":"input","kwarg":false,"opt":false,"tfjs":"a"},{"name":"other","kwarg":false,"opt":false,"tfjs":"b"},{"name":"out","kwarg":true,"opt":true}],"attrs":["torch","div"],"name":"div","tfjs":"div"}],"erf":[{"args":[{"name":"input","kwarg":false,"opt":false,"tfjs":"a"},{"name":"out","kwarg":true,"opt":true}],"attrs":["torch","erf"],"name":"erf","tfjs":"erf","tf":"erf"}],"exp":[{"args":[{"name":"input","kwarg":false,"opt":false,"tfjs":"a"},{"name":"out","kwarg":true,"opt":true}],"attrs":["torch","exp"],"name":"exp","tfjs":"exp","tf":"exp"}],"expm1":[{"args":[{"name":"input","kwarg":false,"opt":false,"tfjs":"a"},{"name":"out","kwarg":true,"opt":true}],"attrs":["torch","expm1"],"name":"expm1","tfjs":"expm1","tf":"expm1"}],"floor":[{"args":[{"name":"input","kwarg":false,"opt":false,"tfjs":"a"},{"name":"out","kwarg":true,"opt":true}],"attrs":["torch","floor"],"name":"floor","tfjs":"floor","tf":"floor"}],"imag":[{"args":[{"name":"input","kwarg":false,"opt":false,"tfjs":"input","tf":"input"},{"name":"out","kwarg":true,"opt":true}],"attrs":["torch","imag"],"name":"imag","tfjs":"imag","tf":"imag"}],"log":[{"args":[{"name":"input","kwarg":false,"opt":false,"tfjs":"a"},{"name":"out","kwarg":true,"opt":true}],"attrs":["torch","log"],"name":"log","tfjs":"log","tf":"log"}],"log1p":[{"args":[{"name":"input","kwarg":false,"opt":false,"tfjs":"a"},{"name":"out","kwarg":true,"opt":true}],"attrs":["torch","log1p"],"name":"log1p","tfjs":"log1p","tf":"log1p"}],"mul":[{"args":[{"name":"input","kwarg":false,"opt":false,"tfjs":"a"},{"name":"other","kwarg":false,"opt":false,"tfjs":"b"},{"name":"out","kwarg":true,"opt":true}],"attrs":["torch","mul"],"name":"mul","tfjs":"mul"}],"neg":[{"args":[{"name":"input","kwarg":false,"opt":false,"tfjs":"a"},{"name":"out","kwarg":true,"opt":true}],"attrs":["torch","neg"],"name":"neg","tfjs":"neg"}],"pow":[{"args":[{"name":"self","kwarg":false,"opt":false},{"name":"exponent","kwarg":false,"opt":false},{"name":"out","kwarg":true,"opt":true}],"attrs":["torch","pow"],"name":"pow","tfjs":"pow","tf":"pow"}],"real":[{"args":[{"name":"input","kwarg":false,"opt":false,"tfjs":"input","tf":"input"},{"name":"out","kwarg":true,"opt":true}],"attrs":["torch","real"],"name":"real","tfjs":"real","tf":"real"}],"reciprocal":[{"args":[{"name":"input","kwarg":false,"opt":false,"tfjs":"a"},{"name":"out","kwarg":true,"opt":true}],"attrs":["torch","reciprocal"],"name":"reciprocal","tfjs":"reciprocal","tf":"reciprocal"}],"round":[{"args":[{"name":"input","kwarg":false,"opt":false,"tfjs":"a"},{"name":"out","kwarg":true,"opt":true}],"attrs":["torch","round"],"name":"round","tfjs":"round","tf":"round"}],"rsqrt":[{"args":[{"name":"input","kwarg":false,"opt":false,"tfjs":"a"},{"name":"out","kwarg":true,"opt":true}],"attrs":["torch","rsqrt"],"name":"rsqrt","tfjs":"rsqrt","tf":"rsqrt"}],"sign":[{"args":[{"name":"input","kwarg":false,"opt":false,"tfjs":"a"},{"name":"out","kwarg":true,"opt":true}],"attrs":["torch","sign"],"name":"sign","tfjs":"sign","tf":"sign"}],"sin":[{"args":[{"name":"input","kwarg":false,"opt":false,"tfjs":"a"},{"name":"out","kwarg":true,"opt":true}],"attrs":["torch","sin"],"name":"sin","tfjs":"sin","tf":"sin"}],"sinh":[{"args":[{"name":"input","kwarg":false,"opt":false,"tfjs":"a"},{"name":"out","kwarg":true,"opt":true}],"attrs":["torch","sinh"],"name":"sinh","tfjs":"sinh","tf":"sinh"}],"sqrt":[{"args":[{"name":"input","kwarg":false,"opt":false,"tfjs":"a"},{"name":"out","kwarg":true,"opt":true}],"attrs":["torch","sqrt"],"name":"sqrt","tfjs":"sqrt","tf":"sqrt"}],"tan":[{"args":[{"name":"input","kwarg":false,"opt":false,"tfjs":"a"},{"name":"out","kwarg":true,"opt":true}],"attrs":["torch","tan"],"name":"tan","tfjs":"tan","tf":"tan"}],"argmax":[{"args":[{"name":"input","kwarg":false,"opt":false,"tfjs":"a"},{"name":"dim","kwarg":false,"opt":false,"tfjs":"axis"},{"name":"keepdim","kwarg":true,"opt":true}],"attrs":["torch","argmax"],"name":"argmax","tfjs":"argmax","tf":"argmax"}],"argmin":[{"args":[{"name":"input","kwarg":false,"opt":false,"tfjs":"a"},{"name":"dim","kwarg":false,"opt":false,"tfjs":"axis"},{"name":"keepdim","kwarg":true,"opt":true},{"name":"out","kwarg":true,"opt":true}],"attrs":["torch","argmin"],"name":"argmin","tfjs":"argmin","tf":"argmin"}],"logsumexp":[{"args":[{"name":"input","kwarg":false,"opt":false,"tfjs":"a"},{"name":"dim","kwarg":false,"opt":false,"tfjs":"axis"},{"name":"keepdim","kwarg":true,"opt":true},{"name":"out","kwarg":true,"opt":true}],"attrs":["torch","logsumexp"],"name":"logsumexp","tfjs":"logsumexp"}],"mean":[{"args":[{"name":"input","kwarg":false,"opt":false,"tfjs":"a"},{"name":"dim","kwarg":false,"opt":false,"tfjs":"axis"},{"name":"keepdim","kwarg":true,"opt":true},{"name":"out","kwarg":true,"opt":true}],"attrs":["torch","mean"],"name":"mean","tfjs":"mean","tf":"mean"}],"norm":[{"args":[{"name":"input","kwarg":false,"opt":false,"tfjs":"a"},{"name":"p","kwarg":true,"opt":true},{"name":"dim","kwarg":true,"opt":true,"tfjs":"axis"},{"name":"keepdim","kwarg":true,"opt":true},{"name":"out","kwarg":true,"opt":true},{"name":"dtype","kwarg":true,"opt":true}],"attrs":["torch","norm"],"name":"norm","tfjs":"norm","tf":"norm"}],"prod":[{"args":[{"name":"input","kwarg":false,"opt":false,"tfjs":"a"},{"name":"dim","kwarg":false,"opt":false,"tfjs":"axis"},{"name":"keepdim","kwarg":true,"opt":true},{"name":"dtype","kwarg":true,"opt":true}],"attrs":["torch","prod"],"name":"prod","tfjs":"prod","tf":"prod"}],"eq":[{"args":[{"name":"input","kwarg":false,"opt":false,"tfjs":"a"},{"name":"other","kwarg":false,"opt":false,"tfjs":"b"},{"name":"out","kwarg":true,"opt":true}],"attrs":["torch","eq"],"name":"eq","tfjs":"equal"}],"equal":[{"args":[{"name":"input","kwarg":false,"opt":false,"tfjs":"a"},{"name":"other","kwarg":false,"opt":false,"tfjs":"b"}],"attrs":["torch","equal"],"name":"equal","tfjs":"equal","tf":"equal"}],"gt":[{"args":[{"name":"input","kwarg":false,"opt":false,"tfjs":"a"},{"name":"other","kwarg":false,"opt":false,"tfjs":"b"},{"name":"out","kwarg":true,"opt":true}],"attrs":["torch","gt"],"name":"gt","tfjs":"greater"}],"isfinite":[{"args":[],"attrs":["torch","isfinite"],"name":"isfinite","tfjs":"isfinite"}],"isinf":[{"args":[{"name":"tensor","kwarg":false,"opt":false}],"attrs":["torch","isinf"],"name":"isinf","tfjs":"isinf"}],"isnan":[{"args":[],"attrs":["torch","isnan"],"name":"isnan","tfjs":"isnan"}],"max":[{"args":[{"name":"input","kwarg":false,"opt":false,"tfjs":"a"},{"name":"other","kwarg":false,"opt":false,"tfjs":"b"},{"name":"out","kwarg":true,"opt":true}],"attrs":["torch","max"],"name":"max","tfjs":"max","tf":"max"}],"min":[{"args":[{"name":"input","kwarg":false,"opt":false,"tfjs":"a"},{"name":"other","kwarg":false,"opt":false,"tfjs":"b"},{"name":"out","kwarg":true,"opt":true}],"attrs":["torch","min"],"name":"min","tfjs":"min","tf":"min"}],"topk":[{"args":[{"name":"input","kwarg":false,"opt":false,"tfjs":"a"},{"name":"k","kwarg":false,"opt":false,"tfjs":"k"},{"name":"dim","kwarg":true,"opt":true,"tfjs":"axis"},{"name":"largest","kwarg":true,"opt":true},{"name":"sorted","kwarg":true,"opt":true,"tfjs":"sorted"},{"name":"out","kwarg":true,"opt":true}],"attrs":["torch","topk"],"name":"topk","tfjs":"topk"}],"fft":[{"args":[{"name":"input","kwarg":false,"opt":false,"tfjs":"input","tf":"input"},{"name":"signal_ndim","kwarg":false,"opt":false},{"name":"normalized","kwarg":true,"opt":true}],"attrs":["torch","fft"],"name":"fft","tfjs":"fft","tf":"fft"}],"ifft":[{"args":[{"name":"input","kwarg":false,"opt":false,"tfjs":"input","tf":"input"},{"name":"signal_ndim","kwarg":false,"opt":false},{"name":"normalized","kwarg":true,"opt":true}],"attrs":["torch","ifft"],"name":"ifft","tfjs":"ifft","tf":"ifft"}],"rfft":[{"args":[{"name":"input","kwarg":false,"opt":false,"tfjs":"input"},{"name":"signal_ndim","kwarg":false,"opt":false},{"name":"normalized","kwarg":true,"opt":true},{"name":"onesided","kwarg":true,"opt":true}],"attrs":["torch","rfft"],"name":"rfft","tfjs":"rfft","tf":"rfft"}],"irfft":[{"args":[{"name":"input","kwarg":false,"opt":false,"tfjs":"input"},{"name":"signal_ndim","kwarg":false,"opt":false},{"name":"normalized","kwarg":true,"opt":true},{"name":"onesided","kwarg":true,"opt":true},{"name":"signal_sizes","kwarg":true,"opt":true}],"attrs":["torch","irfft"],"name":"irfft","tfjs":"irfft","tf":"irfft"}],"stft":[{"args":[{"name":"input","kwarg":false,"opt":false,"tfjs":"a"},{"name":"n_fft","kwarg":false,"opt":false},{"name":"hop_length","kwarg":true,"opt":true},{"name":"win_length","kwarg":true,"opt":true},{"name":"window","kwarg":true,"opt":true},{"name":"center","kwarg":true,"opt":true},{"name":"pad_mode","kwarg":true,"opt":true},{"name":"normalized","kwarg":true,"opt":true},{"name":"onesided","kwarg":true,"opt":true}],"attrs":["torch","stft"],"name":"stft","tfjs":"stft","tf":"stft"}],"cumsum":[{"args":[{"name":"input","kwarg":false,"opt":false,"tfjs":"a"},{"name":"dim","kwarg":false,"opt":false,"tfjs":"axis"},{"name":"out","kwarg":true,"opt":true},{"name":"dtype","kwarg":true,"opt":true}],"attrs":["torch","cumsum"],"name":"cumsum","tfjs":"cumsum","tf":"cumsum"}],"flatten":[{"args":[{"name":"input","kwarg":false,"opt":false,"tfjs":"a"},{"name":"start_dim","kwarg":true,"opt":true},{"name":"end_dim","kwarg":true,"opt":true}],"attrs":["torch","flatten"],"name":"flatten","tfjs":"flatten","tf":"flatten"}],"dot":[{"args":[{"name":"input","kwarg":false,"opt":false,"tfjs":"a"},{"name":"tensor","kwarg":false,"opt":false}],"attrs":["torch","dot"],"name":"dot","tfjs":"dot","tf":"dot"}],"matmul":[{"args":[{"name":"input","kwarg":false,"opt":false,"tfjs":"a"},{"name":"other","kwarg":false,"opt":false,"tfjs":"b"},{"name":"out","kwarg":true,"opt":true}],"attrs":["torch","matmul"],"name":"matmul","tfjs":"matmul","tf":"matmul"}],"qr":[{"args":[{"name":"input","kwarg":false,"opt":false,"tfjs":"a","tf":"input"},{"name":"some","kwarg":true,"opt":true},{"name":"out","kwarg":true,"opt":true}],"attrs":["torch","qr"],"name":"qr","tfjs":"qr","tf":"qr"}],"truediv":[{"args":[{"name":"input","kwarg":false,"opt":false,"tfjs":"x"},{"name":"other","kwarg":false,"opt":false,"tfjs":"y"},{"name":"out","kwarg":true,"opt":true}],"attrs":["torch","div"],"name":"truediv","tfjs":"div","tf":"truediv"}],"sub":[{"args":[{"name":"value","kwarg":false,"opt":false,"tfjs":"a"},{"name":"other","kwarg":false,"opt":false,"tfjs":"b"}],"attrs":["torch","sub"],"name":"sub","tfjs":"sub"}]},"tfjs":{"tensor":[{"args":[{"name":"values","kwarg":false,"opt":false},{"name":"shape","kwarg":false,"opt":true},{"name":"dtype","kwarg":false,"opt":true,"torch":"dtype","tf":"dtype"}],"attrs":["tf","tensor"],"name":"tensor","torch":"tensor","tf":"tensor"}],"eye":[{"args":[{"name":"numrows","kwarg":false,"opt":false},{"name":"numcolumns","kwarg":false,"opt":true},{"name":"batchshape","kwarg":false,"opt":true},{"name":"dtype","kwarg":false,"opt":true,"torch":"dtype","tf":"dtype"}],"attrs":["tf","eye"],"name":"eye","torch":"eye","tf":"eye"}],"imag":[{"args":[{"name":"input","kwarg":false,"opt":false,"torch":"input","tf":"input"}],"attrs":["tf","imag"],"name":"imag","torch":"imag","tf":"imag"}],"linspace":[{"args":[{"name":"start","kwarg":false,"opt":false,"torch":"start","tf":"start"},{"name":"stop","kwarg":false,"opt":false,"tf":"stop"},{"name":"num","kwarg":false,"opt":false,"tf":"num"}],"attrs":["tf","linspace"],"name":"linspace","torch":"linspace","tf":"linspace"}],"ones":[{"args":[],"attrs":["tf","initializers","ones"],"name":"ones","torch":"ones","tf":"ones"}],"range":[{"args":[{"name":"start","kwarg":false,"opt":false,"torch":"start"},{"name":"stop","kwarg":false,"opt":false},{"name":"step","kwarg":false,"opt":true,"torch":"step"},{"name":"dtype","kwarg":false,"opt":true,"torch":"dtype","tf":"dtype"}],"attrs":["tf","range"],"name":"range","torch":"range","tf":"range"}],"real":[{"args":[{"name":"input","kwarg":false,"opt":false,"torch":"input","tf":"input"}],"attrs":["tf","real"],"name":"real","torch":"real","tf":"real"}],"zeros":[{"args":[],"attrs":["tf","initializers","zeros"],"name":"zeros","torch":"zeros","tf":"zeros"}],"flatten":[{"args":[{"name":"arr","kwarg":false,"opt":false},{"name":"result","kwarg":false,"opt":true},{"name":"skiptypedarray","kwarg":false,"opt":true}],"attrs":["tf","util","flatten"],"name":"flatten","torch":"flatten","tf":"flatten"}],"reshape":[{"args":[{"name":"args","kwarg":false,"opt":false}],"attrs":["tf","layers","reshape"],"name":"reshape","torch":"reshape","tf":"reshape"}],"cumsum":[{"args":[{"name":"x","kwarg":false,"opt":false,"tf":"x"},{"name":"axis","kwarg":false,"opt":true,"tf":"axis"},{"name":"exclusive","kwarg":false,"opt":true},{"name":"reverse","kwarg":false,"opt":true}],"attrs":["tf","cumsum"],"name":"cumsum","torch":"cumsum","tf":"cumsum"}],"squeeze":[{"args":[{"name":"x","kwarg":false,"opt":false},{"name":"axis","kwarg":false,"opt":true,"tf":"axis"}],"attrs":["tf","squeeze"],"name":"squeeze","torch":"squeeze","tf":"squeeze"}],"pad":[{"args":[{"name":"x","kwarg":false,"opt":false},{"name":"paddings","kwarg":false,"opt":false,"tf":"paddings"},{"name":"constantvalue","kwarg":false,"opt":true}],"attrs":["tf","pad"],"name":"pad","torch":"pad","tf":"pad"}],"gather":[{"args":[{"name":"x","kwarg":false,"opt":false},{"name":"indices","kwarg":false,"opt":false,"tf":"indices"},{"name":"axis","kwarg":false,"opt":true,"tf":"axis"}],"attrs":["tf","gather"],"name":"gather","torch":"gather","tf":"gather"}],"split":[{"args":[{"name":"x","kwarg":false,"opt":false},{"name":"numorsizesplits","kwarg":false,"opt":false},{"name":"axis","kwarg":false,"opt":true,"tf":"axis"}],"attrs":["tf","split"],"name":"split","torch":"split","tf":"split"}],"stack":[{"args":[{"name":"tensors","kwarg":false,"opt":false,"torch":"tensors"},{"name":"axis","kwarg":false,"opt":true,"tf":"axis"}],"attrs":["tf","stack"],"name":"stack","torch":"stack","tf":"stack"}],"multinomial":[{"args":[{"name":"logits","kwarg":false,"opt":false},{"name":"numsamples","kwarg":false,"opt":false},{"name":"seed","kwarg":false,"opt":true},{"name":"normalized","kwarg":false,"opt":true}],"attrs":["tf","multinomial"],"name":"multinomial","torch":"multinomial"}],"add":[{"args":[{"name":"a","kwarg":false,"opt":false},{"name":"b","kwarg":false,"opt":false}],"attrs":["tf","add"],"name":"add","torch":"add","tf":"add"}],"elu":[{"args":[{"name":"x","kwarg":false,"opt":false,"tf":"x"}],"attrs":["tf","elu"],"name":"elu","torch":"elu","tf":"elu"}],"prelu":[{"args":[{"name":"x","kwarg":false,"opt":false},{"name":"alpha","kwarg":false,"opt":false}],"attrs":["tf","prelu"],"name":"prelu","torch":"prelu","tf":"prelu"}],"relu":[{"args":[{"name":"x","kwarg":false,"opt":false,"tf":"x"}],"attrs":["tf","relu"],"name":"relu","torch":"relu","tf":"relu"}],"softmax":[{"args":[{"name":"logits","kwarg":false,"opt":false},{"name":"dim","kwarg":false,"opt":true,"torch":"dim"}],"attrs":["tf","softmax"],"name":"softmax","torch":"softmax","tf":"softmax"}],"dropout":[{"args":[{"name":"x","kwarg":false,"opt":false,"tf":"x"},{"name":"rate","kwarg":false,"opt":false},{"name":"noiseshape","kwarg":false,"opt":true},{"name":"seed","kwarg":false,"opt":true,"tf":"seed"}],"attrs":["tf","dropout"],"name":"dropout","torch":"dropout","tf":"dropout"}],"embedding":[{"args":[{"name":"args","kwarg":false,"opt":false}],"attrs":["tf","layers","embedding"],"name":"embedding","torch":"embedding","tf":"embedding"}],"conv1d":[{"args":[{"name":"x","kwarg":false,"opt":false,"tf":"x"},{"name":"filter","kwarg":false,"opt":false},{"name":"stride","kwarg":false,"opt":false,"torch":"stride"},{"name":"pad","kwarg":false,"opt":false},{"name":"dataformat","kwarg":false,"opt":true},{"name":"dilation","kwarg":false,"opt":true,"torch":"dilation"},{"name":"dimroundingmode","kwarg":false,"opt":true}],"attrs":["tf","conv1d"],"name":"conv1d","torch":"conv1d","tf":"conv1d"}],"conv2d":[{"args":[{"name":"x","kwarg":false,"opt":false,"tf":"x"},{"name":"filter","kwarg":false,"opt":false},{"name":"strides","kwarg":false,"opt":false,"tf":"strides"},{"name":"pad","kwarg":false,"opt":false},{"name":"dataformat","kwarg":false,"opt":true},{"name":"dilations","kwarg":false,"opt":true},{"name":"dimroundingmode","kwarg":false,"opt":true}],"attrs":["tf","conv2d"],"name":"conv2d","torch":"conv2d","tf":"conv2d"}],"conv3d":[{"args":[{"name":"x","kwarg":false,"opt":false,"tf":"x"},{"name":"filter","kwarg":false,"opt":false},{"name":"strides","kwarg":false,"opt":false,"tf":"strides"},{"name":"pad","kwarg":false,"opt":false},{"name":"dataformat","kwarg":false,"opt":true},{"name":"dilations","kwarg":false,"opt":true}],"attrs":["tf","conv3d"],"name":"conv3d","torch":"conv3d","tf":"conv3d"}],"dot":[{"args":[{"name":"t1","kwarg":false,"opt":false},{"name":"t2","kwarg":false,"opt":false}],"attrs":["tf","dot"],"name":"dot","torch":"dot","tf":"dot"}],"sub":[{"args":[{"name":"a","kwarg":false,"opt":false},{"name":"b","kwarg":false,"opt":false}],"attrs":["tf","sub"],"name":"sub","torch":"sub"}],"mul":[{"args":[{"name":"a","kwarg":false,"opt":false},{"name":"b","kwarg":false,"opt":false}],"attrs":["tf","mul"],"name":"mul","torch":"mul"}],"div":[{"args":[{"name":"a","kwarg":false,"opt":false},{"name":"b","kwarg":false,"opt":false}],"attrs":["tf","div"],"name":"div","torch":"div"}],"pow":[{"args":[{"name":"base","kwarg":false,"opt":false},{"name":"exp","kwarg":false,"opt":false}],"attrs":["tf","pow"],"name":"pow","torch":"pow","tf":"pow"}],"abs":[{"args":[{"name":"x","kwarg":false,"opt":false,"tf":"x"}],"attrs":["tf","abs"],"name":"abs","torch":"abs","tf":"abs"}],"acos":[{"args":[{"name":"x","kwarg":false,"opt":false,"tf":"x"}],"attrs":["tf","acos"],"name":"acos","torch":"acos","tf":"acos"}],"asin":[{"args":[{"name":"x","kwarg":false,"opt":false,"tf":"x"}],"attrs":["tf","asin"],"name":"asin","torch":"asin","tf":"asin"}],"atan":[{"args":[{"name":"x","kwarg":false,"opt":false,"tf":"x"}],"attrs":["tf","atan"],"name":"atan","torch":"atan","tf":"atan"}],"atan2":[{"args":[{"name":"a","kwarg":false,"opt":false},{"name":"b","kwarg":false,"opt":false}],"attrs":["tf","atan2"],"name":"atan2","torch":"atan2","tf":"atan2"}],"ceil":[{"args":[{"name":"x","kwarg":false,"opt":false,"tf":"x"}],"attrs":["tf","ceil"],"name":"ceil","torch":"ceil","tf":"ceil"}],"cos":[{"args":[{"name":"x","kwarg":false,"opt":false,"tf":"x"}],"attrs":["tf","cos"],"name":"cos","torch":"cos","tf":"cos"}],"cosh":[{"args":[{"name":"x","kwarg":false,"opt":false,"tf":"x"}],"attrs":["tf","cosh"],"name":"cosh","torch":"cosh","tf":"cosh"}],"erf":[{"args":[{"name":"x","kwarg":false,"opt":false,"tf":"x"}],"attrs":["tf","erf"],"name":"erf","torch":"erf","tf":"erf"}],"exp":[{"args":[{"name":"x","kwarg":false,"opt":false,"tf":"x"}],"attrs":["tf","exp"],"name":"exp","torch":"exp","tf":"exp"}],"expm1":[{"args":[{"name":"x","kwarg":false,"opt":false,"tf":"x"}],"attrs":["tf","expm1"],"name":"expm1","torch":"expm1","tf":"expm1"}],"floor":[{"args":[{"name":"x","kwarg":false,"opt":false,"tf":"x"}],"attrs":["tf","floor"],"name":"floor","torch":"floor","tf":"floor"}],"isfinite":[{"args":[{"name":"x","kwarg":false,"opt":false}],"attrs":["tf","isFinite"],"name":"isFinite","torch":"isfinite"}],"isinf":[{"args":[{"name":"x","kwarg":false,"opt":false}],"attrs":["tf","isInf"],"name":"isInf","torch":"isinf"}],"isnan":[{"args":[{"name":"x","kwarg":false,"opt":false}],"attrs":["tf","isNaN"],"name":"isNaN","torch":"isnan"}],"log":[{"args":[{"name":"x","kwarg":false,"opt":false,"tf":"x"}],"attrs":["tf","log"],"name":"log","torch":"log","tf":"log"}],"log1p":[{"args":[{"name":"x","kwarg":false,"opt":false,"tf":"x"}],"attrs":["tf","log1p"],"name":"log1p","torch":"log1p","tf":"log1p"}],"logsigmoid":[{"args":[{"name":"x","kwarg":false,"opt":false}],"attrs":["tf","logSigmoid"],"name":"logSigmoid","torch":"logsigmoid"}],"neg":[{"args":[{"name":"x","kwarg":false,"opt":false}],"attrs":["tf","neg"],"name":"neg","torch":"neg"}],"reciprocal":[{"args":[{"name":"x","kwarg":false,"opt":false,"tf":"x"}],"attrs":["tf","reciprocal"],"name":"reciprocal","torch":"reciprocal","tf":"reciprocal"}],"relu6":[{"args":[{"name":"x","kwarg":false,"opt":false}],"attrs":["tf","relu6"],"name":"relu6","torch":"relu6","tf":"relu6"}],"round":[{"args":[{"name":"x","kwarg":false,"opt":false,"tf":"x"}],"attrs":["tf","round"],"name":"round","torch":"round","tf":"round"}],"rsqrt":[{"args":[{"name":"x","kwarg":false,"opt":false,"tf":"x"}],"attrs":["tf","rsqrt"],"name":"rsqrt","torch":"rsqrt","tf":"rsqrt"}],"selu":[{"args":[{"name":"x","kwarg":false,"opt":false,"tf":"x"}],"attrs":["tf","selu"],"name":"selu","torch":"selu","tf":"selu"}],"sigmoid":[{"args":[{"name":"x","kwarg":false,"opt":false,"tf":"x"}],"attrs":["tf","sigmoid"],"name":"sigmoid","torch":"sigmoid","tf":"sigmoid"}],"sign":[{"args":[{"name":"x","kwarg":false,"opt":false,"tf":"x"}],"attrs":["tf","sign"],"name":"sign","torch":"sign","tf":"sign"}],"sin":[{"args":[{"name":"x","kwarg":false,"opt":false,"tf":"x"}],"attrs":["tf","sin"],"name":"sin","torch":"sin","tf":"sin"}],"sinh":[{"args":[{"name":"x","kwarg":false,"opt":false,"tf":"x"}],"attrs":["tf","sinh"],"name":"sinh","torch":"sinh","tf":"sinh"}],"softplus":[{"args":[{"name":"x","kwarg":false,"opt":false,"tf":"x"}],"attrs":["tf","softplus"],"name":"softplus","torch":"softplus","tf":"softplus"}],"sqrt":[{"args":[{"name":"x","kwarg":false,"opt":false,"tf":"x"}],"attrs":["tf","sqrt"],"name":"sqrt","torch":"sqrt","tf":"sqrt"}],"tan":[{"args":[{"name":"x","kwarg":false,"opt":false,"tf":"x"}],"attrs":["tf","tan"],"name":"tan","torch":"tan","tf":"tan"}],"tanh":[{"args":[{"name":"x","kwarg":false,"opt":false,"tf":"x"}],"attrs":["tf","tanh"],"name":"tanh","torch":"tanh","tf":"tanh"}],"matmul":[{"args":[{"name":"a","kwarg":false,"opt":false,"tf":"a"},{"name":"b","kwarg":false,"opt":false,"tf":"b"},{"name":"transposea","kwarg":false,"opt":true},{"name":"transposeb","kwarg":false,"opt":true}],"attrs":["tf","matMul"],"name":"matMul","torch":"matmul","tf":"matmul"}],"norm":[{"args":[{"name":"x","kwarg":false,"opt":false},{"name":"ord","kwarg":false,"opt":true,"tf":"ord"},{"name":"axis","kwarg":false,"opt":true,"tf":"axis"},{"name":"keepdims","kwarg":false,"opt":true,"tf":"keepdims"}],"attrs":["tf","norm"],"name":"norm","torch":"norm","tf":"norm"}],"transpose":[{"args":[{"name":"x","kwarg":false,"opt":false},{"name":"perm","kwarg":false,"opt":true,"tf":"perm"}],"attrs":["tf","transpose"],"name":"transpose","torch":"t","tf":"transpose"}],"all":[{"args":[{"name":"x","kwarg":false,"opt":false,"tf":"x"},{"name":"axis","kwarg":false,"opt":true,"tf":"axis"},{"name":"keepdims","kwarg":false,"opt":true,"tf":"keepdims"}],"attrs":["tf","all"],"name":"all","torch":"all","tf":"all"}],"any":[{"args":[{"name":"x","kwarg":false,"opt":false,"tf":"x"},{"name":"axis","kwarg":false,"opt":true,"tf":"axis"},{"name":"keepdims","kwarg":false,"opt":true,"tf":"keepdims"}],"attrs":["tf","any"],"name":"any","torch":"any","tf":"any"}],"argmax":[{"args":[{"name":"x","kwarg":false,"opt":false,"tf":"x"},{"name":"axis","kwarg":false,"opt":true,"tf":"axis"}],"attrs":["tf","argMax"],"name":"argMax","torch":"argmax","tf":"argmax"}],"argmin":[{"args":[{"name":"x","kwarg":false,"opt":false,"tf":"x"},{"name":"axis","kwarg":false,"opt":true,"tf":"axis"}],"attrs":["tf","argMin"],"name":"argMin","torch":"argmin","tf":"argmin"}],"logsumexp":[{"args":[{"name":"x","kwarg":false,"opt":false},{"name":"axis","kwarg":false,"opt":true},{"name":"keepdims","kwarg":false,"opt":true}],"attrs":["tf","logSumExp"],"name":"logSumExp","torch":"logsumexp"}],"max":[{"args":[{"name":"x","kwarg":false,"opt":false,"tf":"x"},{"name":"axis","kwarg":false,"opt":true,"tf":"axis"},{"name":"keepdims","kwarg":false,"opt":true,"tf":"keepdims"}],"attrs":["tf","max"],"name":"max","torch":"max","tf":"max"}],"mean":[{"args":[{"name":"x","kwarg":false,"opt":false,"tf":"x"},{"name":"axis","kwarg":false,"opt":true,"tf":"axis"},{"name":"keepdims","kwarg":false,"opt":true,"tf":"keepdims"}],"attrs":["tf","mean"],"name":"mean","torch":"mean","tf":"mean"}],"min":[{"args":[{"name":"x","kwarg":false,"opt":false,"tf":"x"},{"name":"axis","kwarg":false,"opt":true,"tf":"axis"},{"name":"keepdims","kwarg":false,"opt":true,"tf":"keepdims"}],"attrs":["tf","min"],"name":"min","torch":"min","tf":"min"}],"prod":[{"args":[{"name":"x","kwarg":false,"opt":false,"tf":"x"},{"name":"axis","kwarg":false,"opt":true,"tf":"axis"},{"name":"keepdims","kwarg":false,"opt":true,"tf":"keepdims"}],"attrs":["tf","prod"],"name":"prod","torch":"prod","tf":"prod"}],"sum":[{"args":[{"name":"x","kwarg":false,"opt":false,"tf":"x"},{"name":"axis","kwarg":false,"opt":true,"tf":"axis"},{"name":"keepdims","kwarg":false,"opt":true,"tf":"keepdims"}],"attrs":["tf","sum"],"name":"sum","torch":"sum","tf":"sum"}],"equal":[{"args":[{"name":"a","kwarg":false,"opt":false},{"name":"b","kwarg":false,"opt":false}],"attrs":["tf","equal"],"name":"equal","torch":"eq","tf":"equal"}],"greater":[{"args":[{"name":"a","kwarg":false,"opt":false},{"name":"b","kwarg":false,"opt":false}],"attrs":["tf","greater"],"name":"greater","torch":"gt","tf":"greater"}],"where":[{"args":[{"name":"condition","kwarg":false,"opt":false,"torch":"condition","tf":"condition"},{"name":"a","kwarg":false,"opt":false},{"name":"b","kwarg":false,"opt":false}],"attrs":["tf","where"],"name":"where","torch":"where","tf":"where"}],"topk":[{"args":[{"name":"x","kwarg":false,"opt":false},{"name":"k","kwarg":false,"opt":true,"torch":"k"},{"name":"sorted","kwarg":false,"opt":true,"torch":"sorted"}],"attrs":["tf","topk"],"name":"topk","torch":"topk"}],"fft":[{"args":[{"name":"input","kwarg":false,"opt":false,"torch":"input","tf":"input"}],"attrs":["tf","spectral","fft"],"name":"fft","torch":"fft","tf":"fft"}],"ifft":[{"args":[{"name":"input","kwarg":false,"opt":false,"torch":"input","tf":"input"}],"attrs":["tf","spectral","ifft"],"name":"ifft","torch":"ifft","tf":"ifft"}],"irfft":[{"args":[{"name":"input","kwarg":false,"opt":false,"torch":"input"}],"attrs":["tf","spectral","irfft"],"name":"irfft","torch":"irfft","tf":"irfft"}],"rfft":[{"args":[{"name":"input","kwarg":false,"opt":false,"torch":"input"},{"name":"fftlength","kwarg":false,"opt":true}],"attrs":["tf","spectral","rfft"],"name":"rfft","torch":"rfft","tf":"rfft"}],"stft":[{"args":[{"name":"signal","kwarg":false,"opt":false},{"name":"framelength","kwarg":false,"opt":false},{"name":"framestep","kwarg":false,"opt":false},{"name":"fftlength","kwarg":false,"opt":true},{"name":"windowfn","kwarg":false,"opt":true}],"attrs":["tf","signal","stft"],"name":"stft","torch":"stft","tf":"stft"}],"qr":[{"args":[{"name":"x","kwarg":false,"opt":false},{"name":"fullmatrices","kwarg":false,"opt":true}],"attrs":["tf","linalg","qr"],"name":"qr","torch":"qr","tf":"qr"}],"grad":[{"args":[{"name":"f","kwarg":false,"opt":false}],"attrs":["tf","grad"],"name":"grad","torch":"grad"}],"identity":[{"args":[{"name":"args","kwarg":false,"opt":false}],"attrs":["tf","initializers","identity"],"name":"identity","torch":"identity","tf":"identity"}],"take":[{"args":[{"name":"count","kwarg":false,"opt":false}],"attrs":["take"],"name":"take","torch":"take"}]}}